dockstring/__init__.py
dockstring/dataset.py
dockstring/errors.py
dockstring/target.py
dockstring/utils.py
dockstring/benchmarks/__init__.py
dockstring/benchmarks/original.py
dockstring/benchmarks/utils.py
dockstring/resources/view_search_box.py
dockstring/resources/bin/LICENSE
dockstring/resources/bin/README.md
dockstring/resources/bin/vina_linux
dockstring/resources/bin/vina_mac_catalina
dockstring/resources/targets/ABL1_conf.txt
dockstring/resources/targets/ABL1_target.pdbqt
dockstring/resources/targets/ACHE_conf.txt
dockstring/resources/targets/ACHE_target.pdbqt
dockstring/resources/targets/ADAM17_conf.txt
dockstring/resources/targets/ADAM17_target.pdbqt
dockstring/resources/targets/ADORA2A_conf.txt
dockstring/resources/targets/ADORA2A_target.pdbqt
dockstring/resources/targets/ADRB1_conf.txt
dockstring/resources/targets/ADRB1_target.pdbqt
dockstring/resources/targets/ADRB2_conf.txt
dockstring/resources/targets/ADRB2_target.pdbqt
dockstring/resources/targets/AKT1_conf.txt
dockstring/resources/targets/AKT1_target.pdbqt
dockstring/resources/targets/AKT2_conf.txt
dockstring/resources/targets/AKT2_target.pdbqt
dockstring/resources/targets/AR_conf.txt
dockstring/resources/targets/AR_target.pdbqt
dockstring/resources/targets/BACE1_conf.txt
dockstring/resources/targets/BACE1_target.pdbqt
dockstring/resources/targets/CA2_conf.txt
dockstring/resources/targets/CA2_target.pdbqt
dockstring/resources/targets/CASP3_conf.txt
dockstring/resources/targets/CASP3_target.pdbqt
dockstring/resources/targets/CDK2_conf.txt
dockstring/resources/targets/CDK2_target.pdbqt
dockstring/resources/targets/CSF1R_conf.txt
dockstring/resources/targets/CSF1R_target.pdbqt
dockstring/resources/targets/CYP2C9_conf.txt
dockstring/resources/targets/CYP2C9_target.pdbqt
dockstring/resources/targets/CYP3A4_conf.txt
dockstring/resources/targets/CYP3A4_target.pdbqt
dockstring/resources/targets/DHFR_conf.txt
dockstring/resources/targets/DHFR_target.pdbqt
dockstring/resources/targets/DPP4_conf.txt
dockstring-0.3.4.dist-info/LICENSE
dockstring-0.3.4.dist-info/METADATA
dockstring-0.3.4.dist-info/WHEEL
dockstring-0.3.4.dist-info/top_level.txt
dockstring-0.3.4.dist-info/RECORD
