Metadata-Version: 2.1
Name: dockstring
Version: 0.3.4
Summary: Package for easy ligand preparation and docking with AutoDock Vina against a highly-curated selection of 58 protein targets. One of the three components of the DOCKSTRING bundle (package, dataset, and benchmark tasks).
Author: Miguel García-Ortegón, Gregor Simm, Austin Tripp
License: 
Project-URL: Homepage, https://github.com/dockstring/dockstring
Project-URL: Repository, https://github.com/dockstring/dockstring.git
Project-URL: Changelog, https://github.com/dockstring/dockstring/blob/main/CHANGELOG.md
Keywords: docking,ligand,protein,binding,benchmark
Requires-Python: >=3.7
License-File: LICENSE
Provides-Extra: dev
Requires-Dist: pytest ; extra == 'dev'
Requires-Dist: pre-commit ; extra == 'dev'
